importStar/importstar.py
importStar/__init__.py
importStar-0.1.1.data/scripts/importstar.py
importStar-0.1.1.dist-info/DESCRIPTION.rst
importStar-0.1.1.dist-info/METADATA
importStar-0.1.1.dist-info/metadata.json
importStar-0.1.1.dist-info/RECORD
importStar-0.1.1.dist-info/top_level.txt
importStar-0.1.1.dist-info/WHEEL
