Metadata-Version: 2.0
Name: importStar
Version: 0.1.1
Summary: 
